{"is_source_file": true, "format": "Python", "description": "This file defines a Flask API route for managing receipt files associated with expenses, including uploading, downloading, and deleting receipt files for specific expense entries.", "external_files": ["flask", "flask.views", "flask_smorest", "werkzeug.datastructures", "../db", "../models", "../utils/storage", "../schemas"], "external_methods": ["send_file", "request.files", "abort", "Expense.query.get", "save_receipt_file", "get_receipt_path", "os.path.exists", "os.remove", "db.session.commit"], "published": ["blp"], "classes": [{"name": "ExpenseReceipt", "description": "A Flask MethodView class managing receipt files for a specific expense, providing endpoints for retrieving, uploading, and deleting receipts."}], "methods": [{"name": "get(self, expense_id: int)", "description": "Handles GET requests to download the receipt file for the specified expense.", "scope": "ExpenseReceipt", "scopeKind": "class"}, {"name": "post(self, expense_id: int)", "description": "Handles POST requests to upload or replace the receipt file for the specified expense.", "scope": "ExpenseReceipt", "scopeKind": "class"}, {"name": "delete(self, expense_id: int)", "description": "Handles DELETE requests to remove the receipt file associated with the expense.", "scope": "ExpenseReceipt", "scopeKind": "class"}], "calls": ["Expense.query.get", "get_receipt_path", "os.path.exists", "send_file", "save_receipt_file", "os.remove", "db.session.commit"], "search-terms": ["receipt management", "expense receipt API", "upload receipt", "download receipt", "delete receipt", "Flask MethodView", "receipt file route", "receipt file storage"], "state": 2, "file_id": 13, "knowledge_revision": 28, "git_revision": "", "ctags": [{"_type": "tag", "name": "ExpenseReceipt", "path": "/home/kavia/workspace/code-generation/expense-splitter-with-receipts-158093-158103/backend/app/routes/receipts.py", "pattern": "/^class ExpenseReceipt(MethodView):$/", "language": "Python", "kind": "class"}, {"_type": "tag", "name": "blp", "path": "/home/kavia/workspace/code-generation/expense-splitter-with-receipts-158093-158103/backend/app/routes/receipts.py", "pattern": "/^blp = Blueprint($/", "language": "Python", "kind": "variable"}, {"_type": "tag", "name": "delete", "path": "/home/kavia/workspace/code-generation/expense-splitter-with-receipts-158093-158103/backend/app/routes/receipts.py", "pattern": "/^    def delete(self, expense_id: int):$/", "language": "Python", "kind": "member", "signature": "(self, expense_id: int)", "scope": "ExpenseReceipt", "scopeKind": "class"}, {"_type": "tag", "name": "get", "path": "/home/kavia/workspace/code-generation/expense-splitter-with-receipts-158093-158103/backend/app/routes/receipts.py", "pattern": "/^    def get(self, expense_id: int):$/", "language": "Python", "kind": "member", "signature": "(self, expense_id: int)", "scope": "ExpenseReceipt", "scopeKind": "class"}, {"_type": "tag", "name": "post", "path": "/home/kavia/workspace/code-generation/expense-splitter-with-receipts-158093-158103/backend/app/routes/receipts.py", "pattern": "/^    def post(self, expense_id: int):$/", "language": "Python", "kind": "member", "signature": "(self, expense_id: int)", "scope": "ExpenseReceipt", "scopeKind": "class"}], "hash": "364be3942ff3cc7a19e414595ac1d9d4", "format-version": 4, "code-base-name": "backend", "filename": "backend/app/routes/receipts.py", "fields": [{"name": "blp = Blueprint(", "scope": "", "scopeKind": "", "description": "unavailable"}], "revision_history": [{"28": ""}]}